sc2env/__init__.py
sc2env/play_all.py
sc2env/play_fog_of_war.py
sc2env/play_fog_of_war_multiplayer.py
sc2env/play_four_towers_friendly_unit.py
sc2env/play_four_towers_friendly_units_group_dereward.py
sc2env/play_four_towers_mixed_friendly_unit.py
sc2env/play_macro_strategy.py
sc2env/play_micro_battle.py
sc2env/play_simple_tactical.py
sc2env/play_star_intruders.py
sc2env/play_super_four_towers.py
sc2env/play_tug_of_war.py
sc2env/play_tug_of_war_bigA.py
sc2env/play_zergling_defense.py
sc2env/profiling.py
sc2env/pysc2_util.py
sc2env/q_learning_agent.py
sc2env/random_agent.py
sc2env/representation.py
sc2env/utility.py
sc2env/environments/FourTowerSequentialFriendlyUnits.py
sc2env/environments/__init__.py
sc2env/environments/fog_of_war.py
sc2env/environments/four_towers_friendly_units_group_dereward.py
sc2env/environments/four_towers_multi_unit.py
sc2env/environments/four_towers_sequential.py
sc2env/environments/macro_strategy.py
sc2env/environments/micro_battle.py
sc2env/environments/simple_tactical.py
sc2env/environments/star_intruders.py
sc2env/environments/super_four_towers.py
sc2env/environments/tug_of_war.py
sc2env/environments/tug_of_war_bigA.py
sc2env/environments/zergling_defense.py
sc2env/maps/FogOfWar.SC2Map
sc2env/maps/FourTowerSequentialDecomposed.SC2Map
sc2env/maps/FourTowerSequentialDecomposedFourUnitsRandomComp.SC2Map
sc2env/maps/FourTowersWithFriendlyUnits.SC2Map
sc2env/maps/FourTowersWithFriendlyUnitsFixedEnemies.SC2Map
sc2env/maps/FourTowersWithFriendlyUnitsFixedEnemiesFixedPosition.SC2Map
sc2env/maps/FourTowersWithFriendlyUnitsRandomHP.SC2Map
sc2env/maps/FourTowersWithMixedFriendlyUnitsSimple.SC2Map
sc2env/maps/FourTowesFriendlyunitsDecomposedGroupReward.SC2Map
sc2env/maps/FourTowesFriendlyunitsDecomposedGroupReward_recorder.SC2Map
sc2env/maps/MacroStrategy.SC2Map
sc2env/maps/MicroBattle.SC2Map
sc2env/maps/SimpleTacticalEnvironment.SC2Map
sc2env/maps/StarIntruders.SC2Map
sc2env/maps/StarIntrudersVariantA.SC2Map
sc2env-0.1.16.dist-info/LICENSE
sc2env-0.1.16.dist-info/METADATA
sc2env-0.1.16.dist-info/WHEEL
sc2env-0.1.16.dist-info/top_level.txt
sc2env-0.1.16.dist-info/RECORD
