Metadata-Version: 2.1
Name: sc2env
Version: 0.1.16
Summary: Simple StarCraftII environments for reinforcement learning
Home-page: UNKNOWN
Author: Larry Neal
Author-email: nealla@lwneal.com
License: UNKNOWN
Platform: UNKNOWN
Requires-Dist: numpy
Requires-Dist: torch
Requires-Dist: tqdm
Requires-Dist: gym
Requires-Dist: pysc2
Requires-Dist: imutil
